friTap/__init__.py
friTap/_ssl_log.js
friTap/_ssl_log_legacy.js
friTap/about.py
friTap/android.py
friTap/friTap.py
friTap/fritap_utility.py
friTap/pcap.py
friTap/pcap_utility.py
friTap/ssl_logger.py
friTap/assets/__init__.py
friTap/assets/tcpdump_binaries/README.md
friTap/assets/tcpdump_binaries/tcpdump_arm32_android
friTap/assets/tcpdump_binaries/tcpdump_arm64_android
friTap/assets/tcpdump_binaries/tcpdump_x86_64_android
friTap/assets/tcpdump_binaries/tcpdump_x86_android
fritap-1.4.1.5.dist-info/licenses/LICENSE
tests/__init__.py
tests/conftest.py
tests/agent/__init__.py
tests/agent/test_compilation.py
tests/fixtures/__init__.py
tests/fixtures/mock_objects.py
tests/integration/__init__.py
tests/integration/test_mock_ssl_analysis.py
tests/unit/__init__.py
tests/unit/test_android.py
tests/unit/test_pcap.py
tests/unit/test_ssl_logger.py
fritap-1.4.1.5.dist-info/METADATA
fritap-1.4.1.5.dist-info/WHEEL
fritap-1.4.1.5.dist-info/entry_points.txt
fritap-1.4.1.5.dist-info/top_level.txt
fritap-1.4.1.5.dist-info/RECORD
