Metadata-Version: 2.4
Name: friTap
Version: 1.4.1.5
Summary: Simplifies SSL/TLS traffic analysis and key extraction using Frida across major platforms.
Home-page: https://github.com/fkie-cad/friTap
Author: Daniel Baier, Julian Lengersdorff, Francois Egner, Max Ufer
Author-email: daniel.baier@fkie.fraunhofer.de
License: GPL-3.0-only
Project-URL: Source, https://github.com/fkie-cad/friTap
Project-URL: Issues, https://github.com/fkie-cad/friTap/issues
Project-URL: Documentation, https://fkie-cad.github.io/friTap/
Keywords: mobile,instrumentation,frida,hook,SSL decryption
Classifier: License :: OSI Approved :: GNU General Public License v3 (GPLv3)
Classifier: Operating System :: OS Independent
Classifier: Natural Language :: English
Classifier: Programming Language :: Python :: 3 :: Only
Classifier: Programming Language :: JavaScript
Classifier: Topic :: Security
Classifier: Topic :: Software Development :: Debuggers
Requires-Python: >=3.8
License-File: LICENSE
Requires-Dist: frida>=16.0.0
Requires-Dist: frida-tools>=11.0.0
Requires-Dist: AndroidFridaManager
Requires-Dist: hexdump
Requires-Dist: scapy
Requires-Dist: watchdog
Requires-Dist: click
Requires-Dist: importlib-resources; python_version < "3.9"
Requires-Dist: psutil
Requires-Dist: rich>=13.0.0
Dynamic: author
Dynamic: author-email
Dynamic: classifier
Dynamic: description
Dynamic: description-content-type
Dynamic: home-page
Dynamic: keywords
Dynamic: license
Dynamic: license-file
Dynamic: project-url
Dynamic: requires-dist
Dynamic: requires-python
Dynamic: summary
